kiwisolver-1.4.9.dist-info/RECORD
kiwisolver-1.4.9.dist-info/WHEEL
kiwisolver-1.4.9.dist-info/top_level.txt
kiwisolver-1.4.9.dist-info/METADATA
kiwisolver-1.4.9.dist-info/licenses/LICENSE
kiwisolver/__init__.py
kiwisolver/_cext.cpython-310-darwin.so
kiwisolver/_cext.pyi
kiwisolver/py.typed
kiwisolver/exceptions.py
