Metadata-Version: 2.1
Name: kiwisolver
Version: 1.4.9
Summary: A fast implementation of the Cassowary constraint solver
Author-email: The Nucleic Development Team <sccolbert@gmail.com>
Maintainer-email: "Matthieu C. Dartiailh" <m.dartiailh@gmail.com>
License: =========================
Project-URL: homepage, https://github.com/nucleic/kiwi
Project-URL: documentation, https://kiwisolver.readthedocs.io/en/latest/
Project-URL: repository, https://github.com/nucleic/kiwi
Project-URL: changelog, https://github.com/nucleic/kiwi/blob/main/releasenotes.rst
Classifier: License :: OSI Approved :: BSD License
Classifier: Programming Language :: Python
Classifier: Programming Language :: Python :: 3
Classifier: Programming Language :: Python :: 3.10
Classifier: Programming Language :: Python :: 3.11
Classifier: Programming Language :: Python :: 3.12
Classifier: Programming Language :: Python :: 3.13
Classifier: Programming Language :: Python :: 3.14
Classifier: Programming Language :: Python :: Implementation :: CPython
Classifier: Programming Language :: Python :: Implementation :: PyPy
Requires-Python: >=3.10
License-File: LICENSE
